sbommerge/__init__.py
sbommerge/cli.py
sbommerge/cyclonedx_parser.py
sbommerge/cyclonedxgenerator.py
sbommerge/file.py
sbommerge/generator.py
sbommerge/output.py
sbommerge/package.py
sbommerge/relationship.py
sbommerge/spdx_parser.py
sbommerge/spdxgenerator.py
sbommerge/version.py
sbommerge-0.2.0.dist-info/LICENSE
sbommerge-0.2.0.dist-info/METADATA
sbommerge-0.2.0.dist-info/WHEEL
sbommerge-0.2.0.dist-info/entry_points.txt
sbommerge-0.2.0.dist-info/top_level.txt
sbommerge-0.2.0.dist-info/RECORD
